fladoja/__init__.py
fladoja/admin/__init__.py
fladoja/admin/core.py
fladoja/admin/views.py
fladoja/templates/base.html
fladoja/templates/index.html
fladoja/templates/errors/403.html
fladoja/templates/errors/404.html
fladoja/templates/errors/base_error.html
fladoja-0.1.1.dist-info/licenses/LICENSE
tests/__init__.py
tests/test_basic.py
fladoja-0.1.1.dist-info/METADATA
fladoja-0.1.1.dist-info/WHEEL
fladoja-0.1.1.dist-info/entry_points.txt
fladoja-0.1.1.dist-info/top_level.txt
fladoja-0.1.1.dist-info/RECORD
